robust_vision_benchmark
