Metadata-Version: 1.1
Name: robust-vision-benchmark
Version: 0.8.2
Summary: An HTTP server and client that provides access to Foolbox models and attacks.
Home-page: https://github.com/bethgelab/robust-vision-benchmark
Author: Jonas Rauber & Wieland Brendel
Author-email: opensource@bethgelab.org
License: MIT
Platform: UNKNOWN
Classifier: Development Status :: 3 - Alpha
Classifier: Intended Audience :: Developers
Classifier: Intended Audience :: Science/Research
Classifier: License :: OSI Approved :: MIT License
Classifier: Programming Language :: Python :: 2.7
Classifier: Programming Language :: Python :: 3
Classifier: Programming Language :: Python :: 3.5
Classifier: Programming Language :: Python :: 3.6
Classifier: Topic :: Scientific/Engineering :: Artificial Intelligence
